pyneo4j_ogm/__init__.py
pyneo4j_ogm/core/base.py
pyneo4j_ogm/core/client.py
pyneo4j_ogm/core/node.py
pyneo4j_ogm/core/relationship.py
pyneo4j_ogm/exceptions.py
pyneo4j_ogm/fields/property_options.py
pyneo4j_ogm/fields/relationship_property.py
pyneo4j_ogm/fields/settings.py
pyneo4j_ogm/logger.py
pyneo4j_ogm/migrations/__init__.py
pyneo4j_ogm/migrations/actions/create.py
pyneo4j_ogm/migrations/actions/down.py
pyneo4j_ogm/migrations/actions/init.py
pyneo4j_ogm/migrations/actions/status.py
pyneo4j_ogm/migrations/actions/up.py
pyneo4j_ogm/migrations/cli.py
pyneo4j_ogm/migrations/utils/client.py
pyneo4j_ogm/migrations/utils/defaults.py
pyneo4j_ogm/migrations/utils/migration.py
pyneo4j_ogm/migrations/utils/models.py
pyneo4j_ogm/pydantic_utils.py
pyneo4j_ogm/queries/operators.py
pyneo4j_ogm/queries/query_builder.py
pyneo4j_ogm/queries/types.py
pyneo4j_ogm/queries/validators.py
pyneo4j_ogm-0.6.0.dist-info/LICENSE
pyneo4j_ogm-0.6.0.dist-info/METADATA
pyneo4j_ogm-0.6.0.dist-info/WHEEL
pyneo4j_ogm-0.6.0.dist-info/entry_points.txt
pyneo4j_ogm-0.6.0.dist-info/RECORD
