Metadata-Version: 2.1
Name: pyneo4j-ogm
Version: 0.6.0
Summary: Asynchronous Python OGM for Neo4j
Home-page: https://github.com/groc-prog/pyneo4j-ogm
License: MIT
Keywords: neo4j,python,orm,ogm,async,asynchronous,database,graph-database,pydantic
Author: groc-prog
Author-email: marc.troisner@gmail.com
Maintainer: groc-prog
Maintainer-email: marc.troisner@gmail.com
Requires-Python: >=3.10,<4.0
Classifier: Development Status :: 4 - Beta
Classifier: Intended Audience :: Developers
Classifier: License :: OSI Approved :: MIT License
Classifier: Natural Language :: English
Classifier: Operating System :: OS Independent
Classifier: Programming Language :: Python :: 3
Classifier: Programming Language :: Python :: 3.10
Classifier: Programming Language :: Python :: 3.11
Classifier: Programming Language :: Python :: 3.12
Classifier: Topic :: Database
Classifier: Topic :: Software Development :: Libraries :: Python Modules
Classifier: Typing :: Typed
Requires-Dist: argparse (>=1.4.0,<2.0.0)
Requires-Dist: neo4j (>=5.9.0,<6.0.0)
Requires-Dist: pydantic (>=1.10,<3.0)
Requires-Dist: typing-extensions (>=4.8.0,<5.0.0)
Project-URL: Documentation, https://github.com/groc-prog/pyneo4j-ogm#readme
Project-URL: Repository, https://github.com/groc-prog/pyneo4j-ogm
